[{"title": "EA SPORTS\u2122 FIFA 23", "price": "discount from \u20aa289.00 to \u20aa115.60 (60%)", "release": "29 Sep, 2022", "link": "https://store.steampowered.com/app/1811260/EA_SPORTS_FIFA_23/?snr=1_7_7_151_150_1"}, {"title": "FIFA 22", "price": "\u20aa249.00", "release": "30 Sep, 2021", "link": "https://store.steampowered.com/app/1506830/FIFA_22/?snr=1_7_7_151_150_1"}, {"title": "EA SPORTS\u2122 FIFA 23 Ultimate Team\u2122 Starter Bundle", "price": "\u20aa34.50", "release": "14 Dec, 2022", "link": "https://store.steampowered.com/app/2224220/EA_SPORTS_FIFA_23_Ultimate_Team_Starter_Bundle/?snr=1_7_7_151_150_1"}, {"title": "\u8d4c\u795e\u6a21\u62df\u5668\uff1a\u4e9a\u6d32\u98ce\u4e91God Of Gamblers", "price": "none", "release": "19 Feb, 2023", "link": "https://store.steampowered.com/app/2091550/God_Of_Gamblers/?snr=1_7_7_151_150_1"}, {"title": "Skater XL - The Ultimate Skateboarding Game", "price": "\u20aa149.95", "release": "28 Jul, 2020", "link": "https://store.steampowered.com/app/962730/Skater_XL__The_Ultimate_Skateboarding_Game/?snr=1_7_7_151_150_1"}, {"title": "Pixel Cup Soccer - Ultimate Edition", "price": "\u20aa59.99", "release": "14 Oct, 2022", "link": "https://store.steampowered.com/app/1620540/Pixel_Cup_Soccer__Ultimate_Edition/?snr=1_7_7_151_150_1"}, {"title": "Super Buckyball Tournament", "price": "none", "release": "Coming Soon Wishlist Now!", "link": "https://store.steampowered.com/app/1059110/Super_Buckyball_Tournament/?snr=1_7_7_151_150_1"}, {"title": "Ball 3D: Soccer Online", "price": "discount from \u20aa3.50 to \u20aa1.01 (71%)", "release": "31 Mar, 2017", "link": "https://store.steampowered.com/app/485610/Ball_3D_Soccer_Online/?snr=1_7_7_151_150_1"}, {"title": "Pro 11 - Football Manager Game", "price": "Free To Play", "release": "13 Feb, 2020", "link": "https://store.steampowered.com/app/844960/Pro_11__Football_Manager_Game/?snr=1_7_7_151_150_1"}, {"title": "Kopanito All-Stars Soccer", "price": "\u20aa21.95", "release": "16 Nov, 2016", "link": "https://store.steampowered.com/app/399820/Kopanito_AllStars_Soccer/?snr=1_7_7_151_150_1"}, {"title": "Need for Drive - Open World Multiplayer Racing", "price": "\u20aa14.50", "release": "17 Feb, 2021", "link": "https://store.steampowered.com/app/1531720/Need_for_Drive__Open_World_Multiplayer_Racing/?snr=1_7_7_151_150_1"}, {"title": "Lamp Head", "price": "\u20aa14.50", "release": "1 Jun, 2017", "link": "https://store.steampowered.com/app/603030/Lamp_Head/?snr=1_7_7_151_150_1"}, {"title": "Egyptian Senet", "price": "discount from \u20aa14.50 to \u20aa1.45 (90%)", "release": "20 Aug, 2015", "link": "https://store.steampowered.com/app/391580/Egyptian_Senet/?snr=1_7_7_151_150_1"}, {"title": "Supraball", "price": "Free To Play", "release": "8 Feb, 2019", "link": "https://store.steampowered.com/app/321400/Supraball/?snr=1_7_7_151_150_1"}, {"title": "Yerr Out", "price": "Free", "release": "16 Oct, 2022", "link": "https://store.steampowered.com/app/1963360/Yerr_Out/?snr=1_7_7_151_150_1"}, {"title": "Ball 2D: Soccer Online", "price": "discount from \u20aa3.50 to \u20aa1.01 (71%)", "release": "8 Sep, 2017", "link": "https://store.steampowered.com/app/703940/Ball_2D_Soccer_Online/?snr=1_7_7_151_150_1"}, {"title": "Skater XL - Tampa Pro 2022 Gear Pack For Charity", "price": "\u20aa36.95", "release": "26 May, 2022", "link": "https://store.steampowered.com/app/1952000/Skater_XL__Tampa_Pro_2022_Gear_Pack_For_Charity/?snr=1_7_7_151_150_1"}, {"title": "Drop Hunt - Adventure Puzzle", "price": "\u20aa3.50", "release": "23 Feb, 2017", "link": "https://store.steampowered.com/app/596870/Drop_Hunt__Adventure_Puzzle/?snr=1_7_7_151_150_1"}, {"title": "Head Goal: Soccer Online", "price": "discount from \u20aa3.50 to \u20aa1.01 (71%)", "release": "18 Aug, 2017", "link": "https://store.steampowered.com/app/687850/Head_Goal_Soccer_Online/?snr=1_7_7_151_150_1"}, {"title": "ConflictCraft", "price": "\u20aa3.50", "release": "8 Dec, 2016", "link": "https://store.steampowered.com/app/495570/ConflictCraft/?snr=1_7_7_151_150_1"}, {"title": "Fantasy Quest Solitaire", "price": "\u20aa32.95", "release": "16 Jan, 2018", "link": "https://store.steampowered.com/app/755950/Fantasy_Quest_Solitaire/?snr=1_7_7_151_150_1"}, {"title": "Smart Thief", "price": "discount from \u20aa4.95 to \u20aa1.33 (73%)", "release": "1 Dec, 2020", "link": "https://store.steampowered.com/app/1439170/Smart_Thief/?snr=1_7_7_151_150_1"}, {"title": "Fix Me Up Doc! \u2013 Dark Humor", "price": "discount from \u20aa7.25 to \u20aa3.62 (50%)", "release": "22 Jun, 2017", "link": "https://store.steampowered.com/app/643700/Fix_Me_Up_Doc__Dark_Humor/?snr=1_7_7_151_150_1"}, {"title": "Handball 17", "price": "discount from \u20aa36.95 to \u20aa3.69 (90%)", "release": "15 Nov, 2016", "link": "https://store.steampowered.com/app/526980/Handball_17/?snr=1_7_7_151_150_1"}, {"title": "Pixel Soccer", "price": "none", "release": "Coming soon", "link": "https://store.steampowered.com/app/347700/Pixel_Soccer/?snr=1_7_7_151_150_1"}, {"title": "Pixel Soccer", "price": "none", "release": "Coming soon", "link": "https://store.steampowered.com/app/347700/Pixel_Soccer/?snr=1_7_7_151_150_2"}, {"title": "School Bus Driver Simulator", "price": "\u20aa3.50", "release": "21 May, 2022", "link": "https://store.steampowered.com/app/1977280/School_Bus_Driver_Simulator/?snr=1_7_7_151_150_2"}, {"title": "Serious Fun Football", "price": "\u20aa36.95", "release": "14 Jul, 2022", "link": "https://store.steampowered.com/app/1392560/Serious_Fun_Football/?snr=1_7_7_151_150_2"}, {"title": "Asian Truck Simulator", "price": "\u20aa14.50", "release": "9 Sep, 2022", "link": "https://store.steampowered.com/app/2117080/Asian_Truck_Simulator/?snr=1_7_7_151_150_2"}, {"title": "Control Craft 2", "price": "\u20aa14.50", "release": "15 Feb, 2016", "link": "https://store.steampowered.com/app/439930/Control_Craft_2/?snr=1_7_7_151_150_2"}, {"title": "Fly Fly Tuk Tuk", "price": "\u20aa3.50", "release": "8 Aug, 2022", "link": "https://store.steampowered.com/app/2085510/Fly_Fly_Tuk_Tuk/?snr=1_7_7_151_150_2"}, {"title": "Football Nation VR Tournament 2018  VR Only", "price": "discount from \u20aa55.95 to \u20aa16.78 (70%)", "release": "7 Jun, 2018", "link": "https://store.steampowered.com/app/752520/Football_Nation_VR_Tournament_2018/?snr=1_7_7_151_150_2"}, {"title": "Control Craft 3", "price": "\u20aa3.50", "release": "30 Dec, 2016", "link": "https://store.steampowered.com/app/490910/Control_Craft_3/?snr=1_7_7_151_150_2"}, {"title": "Empire of Empires", "price": "\u20aa10.95", "release": "29 Jul, 2022", "link": "https://store.steampowered.com/app/2082730/Empire_of_Empires/?snr=1_7_7_151_150_2"}, {"title": "Super Club Soccer", "price": "Free To Play", "release": "25 Oct, 2019", "link": "https://store.steampowered.com/app/744980/Super_Club_Soccer/?snr=1_7_7_151_150_2"}, {"title": "Tuk Tuk Extreme Simulator", "price": "\u20aa18.50", "release": "2 May, 2022", "link": "https://store.steampowered.com/app/1967620/Tuk_Tuk_Extreme_Simulator/?snr=1_7_7_151_150_2"}, {"title": "ConflictCraft 2 - Game of the Year Edition", "price": "\u20aa3.50", "release": "10 Feb, 2022", "link": "https://store.steampowered.com/app/1877370/ConflictCraft_2__Game_of_the_Year_Edition/?snr=1_7_7_151_150_2"}, {"title": "The Last Hope: Trump vs Mafia - North Korea", "price": "\u20aa3.50", "release": "20 Jan, 2017", "link": "https://store.steampowered.com/app/581030/The_Last_Hope_Trump_vs_Mafia__North_Korea/?snr=1_7_7_151_150_2"}, {"title": "Shark Assault Simulator", "price": "\u20aa169.95", "release": "10 Jun, 2022", "link": "https://store.steampowered.com/app/1948240/Shark_Assault_Simulator/?snr=1_7_7_151_150_2"}, {"title": "Obelixes Tower Defense", "price": "\u20aa36.95", "release": "18 Jun, 2022", "link": "https://store.steampowered.com/app/2016140/Obelixes_Tower_Defense/?snr=1_7_7_151_150_2"}, {"title": "Japanese Drag Racing (JDM) - \u30b8\u30a7\u30a4\u30c7\u30a3\u30fc\u30a8\u30e0", "price": "\u20aa3.50", "release": "11 Mar, 2021", "link": "https://store.steampowered.com/app/1531730/Japanese_Drag_Racing_JDM/?snr=1_7_7_151_150_2"}, {"title": "The Last Hope", "price": "\u20aa3.50", "release": "29 Aug, 2016", "link": "https://store.steampowered.com/app/522570/The_Last_Hope/?snr=1_7_7_151_150_2"}, {"title": "Put Your Brain On", "price": "\u20aa169.95", "release": "10 May, 2022", "link": "https://store.steampowered.com/app/1971730/Put_Your_Brain_On/?snr=1_7_7_151_150_2"}, {"title": "Free Kick X", "price": "\u20aa3.50", "release": "19 Jan, 2021", "link": "https://store.steampowered.com/app/1485450/Free_Kick_X/?snr=1_7_7_151_150_2"}, {"title": "Police Hot Pursuit", "price": "\u20aa21.95", "release": "2 Jan, 2022", "link": "https://store.steampowered.com/app/1851640/Police_Hot_Pursuit/?snr=1_7_7_151_150_2"}, {"title": "Two Sedans Driving Simulator", "price": "\u20aa36.95", "release": "25 Mar, 2022", "link": "https://store.steampowered.com/app/1917720/Two_Sedans_Driving_Simulator/?snr=1_7_7_151_150_2"}, {"title": "Waves Running Simulator", "price": "\u20aa169.95", "release": "7 Apr, 2022", "link": "https://store.steampowered.com/app/1926630/Waves_Running_Simulator/?snr=1_7_7_151_150_2"}, {"title": "FootRock 2", "price": "none", "release": "16 Jun, 2017", "link": "https://store.steampowered.com/app/576740/FootRock_2/?snr=1_7_7_151_150_2"}, {"title": "Highway Traffic Racer", "price": "\u20aa3.50", "release": "5 Mar, 2021", "link": "https://store.steampowered.com/app/1531750/Highway_Traffic_Racer/?snr=1_7_7_151_150_2"}, {"title": "Arena Drift Master", "price": "\u20aa189.95", "release": "9 Mar, 2022", "link": "https://store.steampowered.com/app/1906320/Arena_Drift_Master/?snr=1_7_7_151_150_2"}, {"title": "Laser League: World Arena - New Motion Pack", "price": "\u20aa7.25", "release": "10 May, 2018", "link": "https://store.steampowered.com/app/770480/Laser_League_World_Arena__New_Motion_Pack/?snr=1_7_7_151_150_3"}, {"title": "Need for Spirit: Off-Road Edition", "price": "\u20aa169.95", "release": "7 Mar, 2019", "link": "https://store.steampowered.com/app/1015470/Need_for_Spirit_OffRoad_Edition/?snr=1_7_7_151_150_3"}, {"title": "Dino Zoo Transport Simulator", "price": "\u20aa43.95", "release": "23 Sep, 2019", "link": "https://store.steampowered.com/app/1155420/Dino_Zoo_Transport_Simulator/?snr=1_7_7_151_150_3"}, {"title": "Space Tower Defense", "price": "\u20aa3.50", "release": "9 Sep, 2021", "link": "https://store.steampowered.com/app/1724020/Space_Tower_Defense/?snr=1_7_7_151_150_3"}, {"title": "Freestyle Football 3 - Nosetu Inc Games", "price": "Free To Play", "release": "26 Mar, 2020", "link": "https://store.steampowered.com/app/1255970/Freestyle_Football_3__Nosetu_Inc_Games/?snr=1_7_7_151_150_3"}, {"title": "USA Truck Simulator", "price": "\u20aa18.50", "release": "25 Mar, 2021", "link": "https://store.steampowered.com/app/1568180/USA_Truck_Simulator/?snr=1_7_7_151_150_3"}, {"title": "The Zombie Smasher", "price": "\u20aa36.95", "release": "18 Jan, 2022", "link": "https://store.steampowered.com/app/1859590/The_Zombie_Smasher/?snr=1_7_7_151_150_3"}, {"title": "The Last Hope: Atomic Bomb - Crypto War", "price": "\u20aa169.95", "release": "6 Apr, 2018", "link": "https://store.steampowered.com/app/801320/The_Last_Hope_Atomic_Bomb__Crypto_War/?snr=1_7_7_151_150_3"}, {"title": "Finger Football", "price": "\u20aa3.50", "release": "17 Feb, 2022", "link": "https://store.steampowered.com/app/1871290/Finger_Football/?snr=1_7_7_151_150_3"}, {"title": "Super Arcade Football", "price": "\u20aa47.95", "release": "6 Sep, 2021", "link": "https://store.steampowered.com/app/420550/Super_Arcade_Football/?snr=1_7_7_151_150_3"}, {"title": "FootRock", "price": "none", "release": "14 Oct, 2016", "link": "https://store.steampowered.com/app/497100/FootRock/?snr=1_7_7_151_150_3"}, {"title": "Zombies Killer Machine", "price": "\u20aa189.95", "release": "6 Jan, 2022", "link": "https://store.steampowered.com/app/1850690/Zombies_Killer_Machine/?snr=1_7_7_151_150_3"}, {"title": "Furious Goal", "price": "\u20aa18.50", "release": "23 Sep, 2019", "link": "https://store.steampowered.com/app/1151400/Furious_Goal/?snr=1_7_7_151_150_3"}, {"title": "Director of Football", "price": "\u20aa36.95", "release": "20 Sep, 2018", "link": "https://store.steampowered.com/app/844900/Director_of_Football/?snr=1_7_7_151_150_3"}, {"title": "Space Hero Line", "price": "\u20aa189.95", "release": "24 Aug, 2017", "link": "https://store.steampowered.com/app/655120/Space_Hero_Line/?snr=1_7_7_151_150_3"}, {"title": "Stadium Renovator", "price": "none", "release": "TBA, Discount at launch", "link": "https://store.steampowered.com/app/948880/Stadium_Renovator/?snr=1_7_7_151_150_3"}, {"title": "Super Spyroxo Adventures: Island of Dnfoo", "price": "none", "release": "TBA", "link": "https://store.steampowered.com/app/2089750/Super_Spyroxo_Adventures_Island_of_Dnfoo/?snr=1_7_7_151_150_3"}, {"title": "Stadium Renovator: First Touch", "price": "Free", "release": "To be announced", "link": "https://store.steampowered.com/app/1907350/Stadium_Renovator_First_Touch/?snr=1_7_7_151_150_3"}, {"title": "\u7f16\u5e74\u53f2OL", "price": "Free To Play", "release": "Coming soon", "link": "https://store.steampowered.com/app/2167640/OL/?snr=1_7_7_151_150_3"}, {"title": "SHOOTER LEAGUE - ROBOT GOAL", "price": "none", "release": "To be announced", "link": "https://store.steampowered.com/app/1973560/SHOOTER_LEAGUE__ROBOT_GOAL/?snr=1_7_7_151_150_3"}, {"title": "Soccer Clubs", "price": "Free To Play", "release": "19 Dec, 2022", "link": "https://store.steampowered.com/app/2187660/Soccer_Clubs/?snr=1_7_7_151_150_3"}, {"title": "FootRock2 VR  VR Only", "price": "none", "release": "Coming soon", "link": "https://store.steampowered.com/app/624960/FootRock2_VR/?snr=1_7_7_151_150_3"}, {"title": "Super Streaker Plus", "price": "\u20aa7.25", "release": "31 Aug, 2018", "link": "https://store.steampowered.com/app/911240/Super_Streaker_Plus/?snr=1_7_7_151_150_3"}, {"title": "Game of Drones  VR Supported", "price": "\u20aa14.50", "release": "6 May, 2020", "link": "https://store.steampowered.com/app/811940/Game_of_Drones/?snr=1_7_7_151_150_3"}, {"title": "\u8db3\u7403\u68a6\u4e4b\u961f", "price": "Free", "release": "28 Sep, 2022", "link": "https://store.steampowered.com/app/1332460/_/?snr=1_7_7_151_150_3"}, {"title": "Fimbul Winter", "price": "\u20aa3.50", "release": "6 May, 2021", "link": "https://store.steampowered.com/app/1605590/Fimbul_Winter/?snr=1_7_7_151_150_4"}, {"title": "Police Radar", "price": "\u20aa3.50", "release": "2 Sep, 2022", "link": "https://store.steampowered.com/app/2109610/Police_Radar/?snr=1_7_7_151_150_4"}, {"title": "Bro, where's My head???", "price": "\u20aa7.25", "release": "25 Mar, 2021", "link": "https://store.steampowered.com/app/1564760/Bro_wheres_My_head/?snr=1_7_7_151_150_4"}, {"title": "Jigsaw Puzzle - Expansion Pack 8", "price": "\u20aa7.25", "release": "30 Oct, 2019", "link": "https://store.steampowered.com/app/1185650/Jigsaw_Puzzle__Expansion_Pack_8/?snr=1_7_7_151_150_4"}, {"title": "WFO World Football Online", "price": "\u20aa55.95", "release": "12 Sep, 2022", "link": "https://store.steampowered.com/app/1964760/WFO_World_Football_Online/?snr=1_7_7_151_150_4"}, {"title": "FootPool", "price": "\u20aa18.50", "release": "25 Sep, 2022", "link": "https://store.steampowered.com/app/2092710/FootPool/?snr=1_7_7_151_150_4"}, {"title": "Beam Car Crash Derby", "price": "\u20aa3.50", "release": "17 Mar, 2021", "link": "https://store.steampowered.com/app/1555880/Beam_Car_Crash_Derby/?snr=1_7_7_151_150_4"}, {"title": "Fimbul Winter VR  VR Supported", "price": "\u20aa3.50", "release": "3 Jun, 2021", "link": "https://store.steampowered.com/app/1631950/Fimbul_Winter_VR/?snr=1_7_7_151_150_4"}, {"title": "Join Rush Attack / \u52a0\u5165\u7a81\u88ad", "price": "\u20aa7.25", "release": "6 Oct, 2021", "link": "https://store.steampowered.com/app/1766270/Join_Rush_Attack/?snr=1_7_7_151_150_4"}, {"title": "Office Strike War - Multiplayer Battle Royale", "price": "\u20aa10.95", "release": "2 Sep, 2021", "link": "https://store.steampowered.com/app/1721050/Office_Strike_War__Multiplayer_Battle_Royale/?snr=1_7_7_151_150_4"}, {"title": "FirePuzzle - Save the House", "price": "\u20aa7.25", "release": "19 Nov, 2021", "link": "https://store.steampowered.com/app/1806460/FirePuzzle__Save_the_House/?snr=1_7_7_151_150_4"}, {"title": "Soccer Simulation", "price": "\u20aa18.50", "release": "29 Nov, 2017", "link": "https://store.steampowered.com/app/719970/Soccer_Simulation/?snr=1_7_7_151_150_4"}, {"title": "Puppy - Classic Jigsaw Puzzles", "price": "\u20aa7.25", "release": "4 Jul, 2019", "link": "https://store.steampowered.com/app/1114450/Puppy__Classic_Jigsaw_Puzzles/?snr=1_7_7_151_150_4"}, {"title": "Kungfu Football Captain", "price": "\u20aa10.95", "release": "27 Sep, 2021", "link": "https://store.steampowered.com/app/1672680/Kungfu_Football_Captain/?snr=1_7_7_151_150_4"}, {"title": "Jigsaw Puzzle - Expansion Pack 3", "price": "\u20aa7.25", "release": "17 Sep, 2019", "link": "https://store.steampowered.com/app/1160170/Jigsaw_Puzzle__Expansion_Pack_3/?snr=1_7_7_151_150_4"}, {"title": "Jigsaw Puzzle - Expansion Pack 2", "price": "\u20aa7.25", "release": "13 Sep, 2019", "link": "https://store.steampowered.com/app/1158930/Jigsaw_Puzzle__Expansion_Pack_2/?snr=1_7_7_151_150_4"}, {"title": "Jigsaw Puzzle - Expansion Pack 6", "price": "\u20aa7.25", "release": "29 Oct, 2019", "link": "https://store.steampowered.com/app/1184920/Jigsaw_Puzzle__Expansion_Pack_6/?snr=1_7_7_151_150_4"}, {"title": "Jigsaw Puzzle - Expansion Pack 7", "price": "\u20aa7.25", "release": "29 Oct, 2019", "link": "https://store.steampowered.com/app/1185210/Jigsaw_Puzzle__Expansion_Pack_7/?snr=1_7_7_151_150_4"}, {"title": "Jigsaw Puzzle - Expansion Pack 4", "price": "\u20aa7.25", "release": "18 Sep, 2019", "link": "https://store.steampowered.com/app/1160960/Jigsaw_Puzzle__Expansion_Pack_4/?snr=1_7_7_151_150_4"}, {"title": "Jigsaw Puzzle - Expansion Pack 10", "price": "\u20aa7.25", "release": "31 Oct, 2019", "link": "https://store.steampowered.com/app/1187160/Jigsaw_Puzzle__Expansion_Pack_10/?snr=1_7_7_151_150_4"}, {"title": "Jigsaw Puzzle - Expansion Pack 9", "price": "\u20aa7.25", "release": "30 Oct, 2019", "link": "https://store.steampowered.com/app/1186420/Jigsaw_Puzzle__Expansion_Pack_9/?snr=1_7_7_151_150_4"}, {"title": "Jigsaw Puzzle - Expansion Pack 5", "price": "\u20aa7.25", "release": "19 Sep, 2019", "link": "https://store.steampowered.com/app/1162260/Jigsaw_Puzzle__Expansion_Pack_5/?snr=1_7_7_151_150_4"}, {"title": "Fantasy Memory Card Game - Expansion Pack 2", "price": "\u20aa3.50", "release": "13 Mar, 2020", "link": "https://store.steampowered.com/app/1259900/Fantasy_Memory_Card_Game__Expansion_Pack_2/?snr=1_7_7_151_150_4"}, {"title": "Laser League: World Arena - Tu Lou Pack", "price": "\u20aa18.50", "release": "8 Dec, 2021", "link": "https://store.steampowered.com/app/1818920/Laser_League_World_Arena__Tu_Lou_Pack/?snr=1_7_7_151_150_4"}, {"title": "FootRock 2 Demo", "price": "Free Demo", "release": "22 Jun, 2017", "link": "https://store.steampowered.com/app/576740/FootRock_2/?snr=1_7_7_151_150_4"}, {"title": "Mahjong Dimensions 3D - Fantasy Avatar One", "price": "\u20aa3.50", "release": "1 Oct, 2019", "link": "https://store.steampowered.com/app/1169090/Mahjong_Dimensions_3D__Fantasy_Avatar_One/?snr=1_7_7_151_150_5"}, {"title": "Mahjong Dimensions 3D - Monster Avatar Two", "price": "\u20aa3.50", "release": "24 Sep, 2019", "link": "https://store.steampowered.com/app/1164780/Mahjong_Dimensions_3D__Monster_Avatar_Two/?snr=1_7_7_151_150_5"}, {"title": "Mahjong Dimensions 3D - Monster Avatar Three", "price": "\u20aa3.50", "release": "24 Sep, 2019", "link": "https://store.steampowered.com/app/1165030/Mahjong_Dimensions_3D__Monster_Avatar_Three/?snr=1_7_7_151_150_5"}, {"title": "Mahjong Dimensions 3D - Fantasy Avatar Two", "price": "\u20aa3.50", "release": "3 Oct, 2019", "link": "https://store.steampowered.com/app/1171680/Mahjong_Dimensions_3D__Fantasy_Avatar_Two/?snr=1_7_7_151_150_5"}, {"title": "Mahjong Dimensions 3D - Pets", "price": "\u20aa3.50", "release": "8 Oct, 2019", "link": "https://store.steampowered.com/app/1173080/Mahjong_Dimensions_3D__Pets/?snr=1_7_7_151_150_5"}, {"title": "Mahjong Dimensions 3D - Strategy One", "price": "\u20aa3.50", "release": "20 Oct, 2019", "link": "https://store.steampowered.com/app/1177900/Mahjong_Dimensions_3D__Strategy_One/?snr=1_7_7_151_150_5"}, {"title": "Mahjong Dimensions 3D - Warrior Avatar One", "price": "\u20aa3.50", "release": "20 Sep, 2019", "link": "https://store.steampowered.com/app/1163310/Mahjong_Dimensions_3D__Warrior_Avatar_One/?snr=1_7_7_151_150_5"}, {"title": "Mahjong Dimensions 3D - Warrior Avatar Two", "price": "\u20aa3.50", "release": "21 Sep, 2019", "link": "https://store.steampowered.com/app/1163650/Mahjong_Dimensions_3D__Warrior_Avatar_Two/?snr=1_7_7_151_150_5"}, {"title": "Mahjong Dimensions 3D - Monster Avatar One", "price": "\u20aa3.50", "release": "24 Sep, 2019", "link": "https://store.steampowered.com/app/1164400/Mahjong_Dimensions_3D__Monster_Avatar_One/?snr=1_7_7_151_150_5"}, {"title": "Memory Card Monsters - Expanded Content 1", "price": "\u20aa3.50", "release": "15 Sep, 2020", "link": "https://store.steampowered.com/app/1412140/Memory_Card_Monsters__Expanded_Content_1/?snr=1_7_7_151_150_5"}, {"title": "Serious Fun Football Demo", "price": "Free Demo", "release": "27 Apr, 2022", "link": "https://store.steampowered.com/app/1392560/Serious_Fun_Football/?snr=1_7_7_151_150_5"}]